{"data":[{"id":"ctry.ng.10.1","address":"Akankpa, Cross River, Nigeria","path":"earth/countries/ng/10/1/data.json"},{"id":"ctry.ng.10.2","address":"Calabar, Cross River, Nigeria","path":"earth/countries/ng/10/2/data.json"},{"id":"ctry.ng.10.3","address":"Gakem, Cross River, Nigeria","path":"earth/countries/ng/10/3/data.json"},{"id":"ctry.ng.10.4","address":"Ikang, Cross River, Nigeria","path":"earth/countries/ng/10/4/data.json"},{"id":"ctry.ng.10.5","address":"Ugep, Cross River, Nigeria","path":"earth/countries/ng/10/5/data.json"}]}