{"data":[{"id":"ctry.bf.19.1","address":"Bobo-Dioulasso, Hauts-Bassins Region, Burkina Faso","path":"earth/countries/bf/19/1/data.json"},{"id":"ctry.bf.19.2","address":"Houndé, Hauts-Bassins Region, Burkina Faso","path":"earth/countries/bf/19/2/data.json"},{"id":"ctry.bf.19.3","address":"Province du Houet, Hauts-Bassins Region, Burkina Faso","path":"earth/countries/bf/19/3/data.json"},{"id":"ctry.bf.19.4","address":"Province du Kénédougou, Hauts-Bassins Region, Burkina Faso","path":"earth/countries/bf/19/4/data.json"},{"id":"ctry.bf.19.5","address":"Province du Tuy, Hauts-Bassins Region, Burkina Faso","path":"earth/countries/bf/19/5/data.json"}]}