{"data":[{"id":"ctry.md.10.1","type":"district","name":"Chisinau","path":"earth/countries/md/10/1/data.json"},{"id":"ctry.md.10.2","type":"district","name":"Ciorescu","path":"earth/countries/md/10/2/data.json"},{"id":"ctry.md.10.3","type":"district","name":"Cricova","path":"earth/countries/md/10/3/data.json"},{"id":"ctry.md.10.4","type":"district","name":"Sîngera","path":"earth/countries/md/10/4/data.json"},{"id":"ctry.md.10.5","type":"district","name":"Stăuceni","path":"earth/countries/md/10/5/data.json"},{"id":"ctry.md.10.6","type":"district","name":"Vadul lui Vodă","path":"earth/countries/md/10/6/data.json"},{"id":"ctry.md.10.7","type":"district","name":"Vatra","path":"earth/countries/md/10/7/data.json"}]}