{"data":[{"id":"ctry.gb.nir.1","type":"district","name":"Ahoghill","path":"earth/countries/gb-nir/1/data.json"},{"id":"ctry.gb.nir.2","type":"district","name":"Annahilt","path":"earth/countries/gb-nir/2/data.json"},{"id":"ctry.gb.nir.3","type":"district","name":"Annalong","path":"earth/countries/gb-nir/3/data.json"},{"id":"ctry.gb.nir.4","type":"district","name":"Antrim","path":"earth/countries/gb-nir/4/data.json"},{"id":"ctry.gb.nir.5","type":"district","name":"Antrim and Newtownabbey","path":"earth/countries/gb-nir/5/data.json"},{"id":"ctry.gb.nir.6","type":"district","name":"Ardglass","path":"earth/countries/gb-nir/6/data.json"},{"id":"ctry.gb.nir.7","type":"district","name":"Ards and North Down","path":"earth/countries/gb-nir/7/data.json"},{"id":"ctry.gb.nir.8","type":"district","name":"Armagh","path":"earth/countries/gb-nir/8/data.json"},{"id":"ctry.gb.nir.9","type":"district","name":"Armagh City Banbridge and Craigavon","path":"earth/countries/gb-nir/9/data.json"},{"id":"ctry.gb.nir.10","type":"district","name":"Ballinamallard","path":"earth/countries/gb-nir/10/data.json"},{"id":"ctry.gb.nir.11","type":"district","name":"Ballintoy Harbour","path":"earth/countries/gb-nir/11/data.json"},{"id":"ctry.gb.nir.12","type":"district","name":"Ballycastle","path":"earth/countries/gb-nir/12/data.json"},{"id":"ctry.gb.nir.13","type":"district","name":"Ballyclare","path":"earth/countries/gb-nir/13/data.json"},{"id":"ctry.gb.nir.14","type":"district","name":"Ballygowan","path":"earth/countries/gb-nir/14/data.json"},{"id":"ctry.gb.nir.15","type":"district","name":"Ballykelly","path":"earth/countries/gb-nir/15/data.json"},{"id":"ctry.gb.nir.16","type":"district","name":"Ballymena","path":"earth/countries/gb-nir/16/data.json"},{"id":"ctry.gb.nir.17","type":"district","name":"Ballymoney","path":"earth/countries/gb-nir/17/data.json"},{"id":"ctry.gb.nir.18","type":"district","name":"Ballynahinch","path":"earth/countries/gb-nir/18/data.json"},{"id":"ctry.gb.nir.19","type":"district","name":"Ballypatrick","path":"earth/countries/gb-nir/19/data.json"},{"id":"ctry.gb.nir.20","type":"district","name":"Ballywalter","path":"earth/countries/gb-nir/20/data.json"},{"id":"ctry.gb.nir.21","type":"district","name":"Banbridge","path":"earth/countries/gb-nir/21/data.json"},{"id":"ctry.gb.nir.22","type":"district","name":"Bangor","path":"earth/countries/gb-nir/22/data.json"},{"id":"ctry.gb.nir.23","type":"district","name":"Belfast","path":"earth/countries/gb-nir/23/data.json"},{"id":"ctry.gb.nir.24","type":"district","name":"Bellaghy","path":"earth/countries/gb-nir/24/data.json"},{"id":"ctry.gb.nir.25","type":"district","name":"Broughshane","path":"earth/countries/gb-nir/25/data.json"},{"id":"ctry.gb.nir.26","type":"district","name":"Bushmills","path":"earth/countries/gb-nir/26/data.json"},{"id":"ctry.gb.nir.27","type":"district","name":"Carnlough","path":"earth/countries/gb-nir/27/data.json"},{"id":"ctry.gb.nir.28","type":"district","name":"Carnmoney","path":"earth/countries/gb-nir/28/data.json"},{"id":"ctry.gb.nir.29","type":"district","name":"Carrickfergus","path":"earth/countries/gb-nir/29/data.json"},{"id":"ctry.gb.nir.30","type":"district","name":"Carryduff","path":"earth/countries/gb-nir/30/data.json"},{"id":"ctry.gb.nir.31","type":"district","name":"Castledawson","path":"earth/countries/gb-nir/31/data.json"},{"id":"ctry.gb.nir.32","type":"district","name":"Castlederg","path":"earth/countries/gb-nir/32/data.json"},{"id":"ctry.gb.nir.33","type":"district","name":"Castlereagh","path":"earth/countries/gb-nir/33/data.json"},{"id":"ctry.gb.nir.34","type":"district","name":"Castlerock","path":"earth/countries/gb-nir/34/data.json"},{"id":"ctry.gb.nir.35","type":"district","name":"Castlewellan","path":"earth/countries/gb-nir/35/data.json"},{"id":"ctry.gb.nir.36","type":"district","name":"Causeway Coast and Glens","path":"earth/countries/gb-nir/36/data.json"},{"id":"ctry.gb.nir.37","type":"district","name":"City of Belfast","path":"earth/countries/gb-nir/37/data.json"},{"id":"ctry.gb.nir.38","type":"district","name":"Coalisland","path":"earth/countries/gb-nir/38/data.json"},{"id":"ctry.gb.nir.39","type":"district","name":"Coleraine","path":"earth/countries/gb-nir/39/data.json"},{"id":"ctry.gb.nir.40","type":"district","name":"Comber","path":"earth/countries/gb-nir/40/data.json"},{"id":"ctry.gb.nir.41","type":"district","name":"Connor","path":"earth/countries/gb-nir/41/data.json"},{"id":"ctry.gb.nir.42","type":"district","name":"Cookstown","path":"earth/countries/gb-nir/42/data.json"},{"id":"ctry.gb.nir.43","type":"district","name":"Craigavon","path":"earth/countries/gb-nir/43/data.json"},{"id":"ctry.gb.nir.44","type":"district","name":"Crossgar","path":"earth/countries/gb-nir/44/data.json"},{"id":"ctry.gb.nir.45","type":"district","name":"Crossmaglen","path":"earth/countries/gb-nir/45/data.json"},{"id":"ctry.gb.nir.46","type":"district","name":"Crumlin","path":"earth/countries/gb-nir/46/data.json"},{"id":"ctry.gb.nir.47","type":"district","name":"Cullybackey","path":"earth/countries/gb-nir/47/data.json"},{"id":"ctry.gb.nir.48","type":"district","name":"Culmore","path":"earth/countries/gb-nir/48/data.json"},{"id":"ctry.gb.nir.49","type":"district","name":"Cushendall","path":"earth/countries/gb-nir/49/data.json"},{"id":"ctry.gb.nir.50","type":"district","name":"Derry","path":"earth/countries/gb-nir/50/data.json"},{"id":"ctry.gb.nir.51","type":"district","name":"Derry City and Strabane","path":"earth/countries/gb-nir/51/data.json"},{"id":"ctry.gb.nir.52","type":"district","name":"Doagh","path":"earth/countries/gb-nir/52/data.json"},{"id":"ctry.gb.nir.53","type":"district","name":"Donaghadee","path":"earth/countries/gb-nir/53/data.json"},{"id":"ctry.gb.nir.54","type":"district","name":"Downpatrick","path":"earth/countries/gb-nir/54/data.json"},{"id":"ctry.gb.nir.55","type":"district","name":"Draperstown","path":"earth/countries/gb-nir/55/data.json"},{"id":"ctry.gb.nir.56","type":"district","name":"Dromore","path":"earth/countries/gb-nir/56/data.json"},{"id":"ctry.gb.nir.57","type":"district","name":"Dundonald","path":"earth/countries/gb-nir/57/data.json"},{"id":"ctry.gb.nir.58","type":"district","name":"Dundrum","path":"earth/countries/gb-nir/58/data.json"},{"id":"ctry.gb.nir.59","type":"district","name":"Dungannon","path":"earth/countries/gb-nir/59/data.json"},{"id":"ctry.gb.nir.60","type":"district","name":"Dungiven","path":"earth/countries/gb-nir/60/data.json"},{"id":"ctry.gb.nir.61","type":"district","name":"Dunloy","path":"earth/countries/gb-nir/61/data.json"},{"id":"ctry.gb.nir.62","type":"district","name":"Eglinton","path":"earth/countries/gb-nir/62/data.json"},{"id":"ctry.gb.nir.63","type":"district","name":"Enniskillen","path":"earth/countries/gb-nir/63/data.json"},{"id":"ctry.gb.nir.64","type":"district","name":"Fermanagh and Omagh","path":"earth/countries/gb-nir/64/data.json"},{"id":"ctry.gb.nir.65","type":"district","name":"Fintona","path":"earth/countries/gb-nir/65/data.json"},{"id":"ctry.gb.nir.66","type":"district","name":"Fivemiletown","path":"earth/countries/gb-nir/66/data.json"},{"id":"ctry.gb.nir.67","type":"district","name":"Garvagh","path":"earth/countries/gb-nir/67/data.json"},{"id":"ctry.gb.nir.68","type":"district","name":"Gilford","path":"earth/countries/gb-nir/68/data.json"},{"id":"ctry.gb.nir.69","type":"district","name":"Glenariff","path":"earth/countries/gb-nir/69/data.json"},{"id":"ctry.gb.nir.70","type":"district","name":"Glenavy","path":"earth/countries/gb-nir/70/data.json"},{"id":"ctry.gb.nir.71","type":"district","name":"Greenisland","path":"earth/countries/gb-nir/71/data.json"},{"id":"ctry.gb.nir.72","type":"district","name":"Greyabbey","path":"earth/countries/gb-nir/72/data.json"},{"id":"ctry.gb.nir.73","type":"district","name":"Hillsborough","path":"earth/countries/gb-nir/73/data.json"},{"id":"ctry.gb.nir.74","type":"district","name":"Holywood","path":"earth/countries/gb-nir/74/data.json"},{"id":"ctry.gb.nir.75","type":"district","name":"Irvinestown","path":"earth/countries/gb-nir/75/data.json"},{"id":"ctry.gb.nir.76","type":"district","name":"Jordanstown","path":"earth/countries/gb-nir/76/data.json"},{"id":"ctry.gb.nir.77","type":"district","name":"Keady","path":"earth/countries/gb-nir/77/data.json"},{"id":"ctry.gb.nir.78","type":"district","name":"Kilkeel","path":"earth/countries/gb-nir/78/data.json"},{"id":"ctry.gb.nir.79","type":"district","name":"Killyleagh","path":"earth/countries/gb-nir/79/data.json"},{"id":"ctry.gb.nir.80","type":"district","name":"Kilrea","path":"earth/countries/gb-nir/80/data.json"},{"id":"ctry.gb.nir.81","type":"district","name":"Kircubbin","path":"earth/countries/gb-nir/81/data.json"},{"id":"ctry.gb.nir.82","type":"district","name":"Larne","path":"earth/countries/gb-nir/82/data.json"},{"id":"ctry.gb.nir.83","type":"district","name":"Limavady","path":"earth/countries/gb-nir/83/data.json"},{"id":"ctry.gb.nir.84","type":"district","name":"Lisburn","path":"earth/countries/gb-nir/84/data.json"},{"id":"ctry.gb.nir.85","type":"district","name":"Lisburn and Castlereagh","path":"earth/countries/gb-nir/85/data.json"},{"id":"ctry.gb.nir.86","type":"district","name":"Lisnaskea","path":"earth/countries/gb-nir/86/data.json"},{"id":"ctry.gb.nir.87","type":"district","name":"Londonderry County Borough","path":"earth/countries/gb-nir/87/data.json"},{"id":"ctry.gb.nir.88","type":"district","name":"Maghera","path":"earth/countries/gb-nir/88/data.json"},{"id":"ctry.gb.nir.89","type":"district","name":"Magherafelt","path":"earth/countries/gb-nir/89/data.json"},{"id":"ctry.gb.nir.90","type":"district","name":"Magheralin","path":"earth/countries/gb-nir/90/data.json"},{"id":"ctry.gb.nir.91","type":"district","name":"Mid and East Antrim","path":"earth/countries/gb-nir/91/data.json"},{"id":"ctry.gb.nir.92","type":"district","name":"Mid Ulster","path":"earth/countries/gb-nir/92/data.json"},{"id":"ctry.gb.nir.93","type":"district","name":"Millisle","path":"earth/countries/gb-nir/93/data.json"},{"id":"ctry.gb.nir.94","type":"district","name":"Moira","path":"earth/countries/gb-nir/94/data.json"},{"id":"ctry.gb.nir.95","type":"district","name":"Moneymore","path":"earth/countries/gb-nir/95/data.json"},{"id":"ctry.gb.nir.96","type":"district","name":"Moy","path":"earth/countries/gb-nir/96/data.json"},{"id":"ctry.gb.nir.97","type":"district","name":"Newcastle","path":"earth/countries/gb-nir/97/data.json"},{"id":"ctry.gb.nir.98","type":"district","name":"Newry","path":"earth/countries/gb-nir/98/data.json"},{"id":"ctry.gb.nir.99","type":"district","name":"Newry Mourne and Down","path":"earth/countries/gb-nir/99/data.json"},{"id":"ctry.gb.nir.100","type":"district","name":"Newtownabbey","path":"earth/countries/gb-nir/100/data.json"},{"id":"ctry.gb.nir.101","type":"district","name":"Newtownards","path":"earth/countries/gb-nir/101/data.json"},{"id":"ctry.gb.nir.102","type":"district","name":"Newtownstewart","path":"earth/countries/gb-nir/102/data.json"},{"id":"ctry.gb.nir.103","type":"district","name":"Omagh","path":"earth/countries/gb-nir/103/data.json"},{"id":"ctry.gb.nir.104","type":"district","name":"Portadown","path":"earth/countries/gb-nir/104/data.json"},{"id":"ctry.gb.nir.105","type":"district","name":"Portaferry","path":"earth/countries/gb-nir/105/data.json"},{"id":"ctry.gb.nir.106","type":"district","name":"Portavogie","path":"earth/countries/gb-nir/106/data.json"},{"id":"ctry.gb.nir.107","type":"district","name":"Portglenone","path":"earth/countries/gb-nir/107/data.json"},{"id":"ctry.gb.nir.108","type":"district","name":"Portrush","path":"earth/countries/gb-nir/108/data.json"},{"id":"ctry.gb.nir.109","type":"district","name":"Portstewart","path":"earth/countries/gb-nir/109/data.json"},{"id":"ctry.gb.nir.110","type":"district","name":"Randalstown","path":"earth/countries/gb-nir/110/data.json"},{"id":"ctry.gb.nir.111","type":"district","name":"Rathfriland","path":"earth/countries/gb-nir/111/data.json"},{"id":"ctry.gb.nir.112","type":"district","name":"Rostrevor","path":"earth/countries/gb-nir/112/data.json"},{"id":"ctry.gb.nir.113","type":"district","name":"Saintfield","path":"earth/countries/gb-nir/113/data.json"},{"id":"ctry.gb.nir.114","type":"district","name":"Sion Mills","path":"earth/countries/gb-nir/114/data.json"},{"id":"ctry.gb.nir.115","type":"district","name":"Strabane","path":"earth/countries/gb-nir/115/data.json"},{"id":"ctry.gb.nir.116","type":"district","name":"Tandragee","path":"earth/countries/gb-nir/116/data.json"},{"id":"ctry.gb.nir.117","type":"district","name":"Templepatrick","path":"earth/countries/gb-nir/117/data.json"},{"id":"ctry.gb.nir.118","type":"district","name":"Waringstown","path":"earth/countries/gb-nir/118/data.json"},{"id":"ctry.gb.nir.119","type":"district","name":"Warrenpoint","path":"earth/countries/gb-nir/119/data.json"},{"id":"ctry.gb.nir.120","type":"district","name":"Whitehead","path":"earth/countries/gb-nir/120/data.json"}]}