{"data":[{"id":"ctry.cn.1.1","address":"Anqing, Anhui, China","path":"earth/countries/cn/1/1/data.json"},{"id":"ctry.cn.1.2","address":"Anqing Shi, Anhui, China","path":"earth/countries/cn/1/2/data.json"},{"id":"ctry.cn.1.3","address":"Bengbu, Anhui, China","path":"earth/countries/cn/1/3/data.json"},{"id":"ctry.cn.1.4","address":"Bozhou, Anhui, China","path":"earth/countries/cn/1/4/data.json"},{"id":"ctry.cn.1.5","address":"Chaohu, Anhui, China","path":"earth/countries/cn/1/5/data.json"},{"id":"ctry.cn.1.6","address":"Chizhou, Anhui, China","path":"earth/countries/cn/1/6/data.json"},{"id":"ctry.cn.1.7","address":"Chizhou Shi, Anhui, China","path":"earth/countries/cn/1/7/data.json"},{"id":"ctry.cn.1.8","address":"Chuzhou, Anhui, China","path":"earth/countries/cn/1/8/data.json"},{"id":"ctry.cn.1.9","address":"Chuzhou Shi, Anhui, China","path":"earth/countries/cn/1/9/data.json"},{"id":"ctry.cn.1.10","address":"Datong, Anhui, China","path":"earth/countries/cn/1/10/data.json"},{"id":"ctry.cn.1.11","address":"Fuyang, Anhui, China","path":"earth/countries/cn/1/11/data.json"},{"id":"ctry.cn.1.12","address":"Fuyang Shi, Anhui, China","path":"earth/countries/cn/1/12/data.json"},{"id":"ctry.cn.1.13","address":"Gushu, Anhui, China","path":"earth/countries/cn/1/13/data.json"},{"id":"ctry.cn.1.14","address":"Hefei, Anhui, China","path":"earth/countries/cn/1/14/data.json"},{"id":"ctry.cn.1.15","address":"Hefei Shi, Anhui, China","path":"earth/countries/cn/1/15/data.json"},{"id":"ctry.cn.1.16","address":"Huaibei, Anhui, China","path":"earth/countries/cn/1/16/data.json"},{"id":"ctry.cn.1.17","address":"Huainan, Anhui, China","path":"earth/countries/cn/1/17/data.json"},{"id":"ctry.cn.1.18","address":"Huainan Shi, Anhui, China","path":"earth/countries/cn/1/18/data.json"},{"id":"ctry.cn.1.19","address":"Huaiyuan Chengguanzhen, Anhui, China","path":"earth/countries/cn/1/19/data.json"},{"id":"ctry.cn.1.20","address":"Huangshan, Anhui, China","path":"earth/countries/cn/1/20/data.json"},{"id":"ctry.cn.1.21","address":"Huangshan Shi, Anhui, China","path":"earth/countries/cn/1/21/data.json"},{"id":"ctry.cn.1.22","address":"Huoqiu Chengguanzhen, Anhui, China","path":"earth/countries/cn/1/22/data.json"},{"id":"ctry.cn.1.23","address":"Jieshou, Anhui, China","path":"earth/countries/cn/1/23/data.json"},{"id":"ctry.cn.1.24","address":"Lu’an, Anhui, China","path":"earth/countries/cn/1/24/data.json"},{"id":"ctry.cn.1.25","address":"Lucheng, Anhui, China","path":"earth/countries/cn/1/25/data.json"},{"id":"ctry.cn.1.26","address":"Mengcheng Chengguanzhen, Anhui, China","path":"earth/countries/cn/1/26/data.json"},{"id":"ctry.cn.1.27","address":"Mingguang, Anhui, China","path":"earth/countries/cn/1/27/data.json"},{"id":"ctry.cn.1.28","address":"Suixi, Anhui, China","path":"earth/countries/cn/1/28/data.json"},{"id":"ctry.cn.1.29","address":"Suzhou, Anhui, China","path":"earth/countries/cn/1/29/data.json"},{"id":"ctry.cn.1.30","address":"Suzhou Shi, Anhui, China","path":"earth/countries/cn/1/30/data.json"},{"id":"ctry.cn.1.31","address":"Tangzhai, Anhui, China","path":"earth/countries/cn/1/31/data.json"},{"id":"ctry.cn.1.32","address":"Wucheng, Anhui, China","path":"earth/countries/cn/1/32/data.json"},{"id":"ctry.cn.1.33","address":"Wuhu, Anhui, China","path":"earth/countries/cn/1/33/data.json"},{"id":"ctry.cn.1.34","address":"Wusong, Anhui, China","path":"earth/countries/cn/1/34/data.json"},{"id":"ctry.cn.1.35","address":"Wuyang, Anhui, China","path":"earth/countries/cn/1/35/data.json"},{"id":"ctry.cn.1.36","address":"Xuanzhou, Anhui, China","path":"earth/countries/cn/1/36/data.json"},{"id":"ctry.cn.1.37","address":"Yingshang Chengguanzhen, Anhui, China","path":"earth/countries/cn/1/37/data.json"}]}